khemia/__init__.py
khemia/cache.py
khemia/typing.py
khemia/utils.py
khemia-0.1.1.dist-info/LICENSE
khemia-0.1.1.dist-info/METADATA
khemia-0.1.1.dist-info/WHEEL
khemia-0.1.1.dist-info/RECORD
